setup.py
MomWebsite.egg-info/PKG-INFO
MomWebsite.egg-info/SOURCES.txt
MomWebsite.egg-info/dependency_links.txt
MomWebsite.egg-info/top_level.txt
mom_website/MomwhyareyouhereWebsite.py
mom_website/__init__.py